LICENSE
MANIFEST.in
README.rst
askbot_fedmsg.py
setup.py
askbot_fedmsg.egg-info/PKG-INFO
askbot_fedmsg.egg-info/SOURCES.txt
askbot_fedmsg.egg-info/dependency_links.txt
askbot_fedmsg.egg-info/not-zip-safe
askbot_fedmsg.egg-info/requires.txt
askbot_fedmsg.egg-info/top_level.txt